.clang-format
.flake8
.gitignore
.gitmodules
CHANGELOG.md
CODEOWNERS
CODE_OF_CONDUCT
Dockerfile
Dockerfile-cuda
Dockerfile-embedded
LICENSE
MANIFEST.in
Makefile
README.md
__init__.py
description.txt
packages.txt
setup.py
./src/opendr/__init__.py
./src/opendr/_setup.py
./src/opendr/_version.py
./src/opendr/control/__init__.py
./src/opendr/engine/__init__.py
./src/opendr/engine/constants.py
./src/opendr/engine/data.py
./src/opendr/engine/datasets.py
./src/opendr/engine/example_learner.py
./src/opendr/engine/learners.py
./src/opendr/engine/target.py
./src/opendr/perception/__init__.py
./src/opendr/perception/multimodal_human_centric/__init__.py
./src/opendr/perception/multimodal_human_centric/dependencies.ini
./src/opendr/perception/multimodal_human_centric/audiovisual_emotion_learner/README.MD
./src/opendr/perception/multimodal_human_centric/audiovisual_emotion_learner/__init__.py
./src/opendr/perception/multimodal_human_centric/audiovisual_emotion_learner/avlearner.py
./src/opendr/perception/multimodal_human_centric/audiovisual_emotion_learner/dependencies.ini
./src/opendr/perception/multimodal_human_centric/audiovisual_emotion_learner/algorithm/__init__.py
./src/opendr/perception/multimodal_human_centric/audiovisual_emotion_learner/algorithm/data.py
./src/opendr/perception/multimodal_human_centric/audiovisual_emotion_learner/algorithm/data_utils.py
./src/opendr/perception/multimodal_human_centric/audiovisual_emotion_learner/algorithm/efficientface_modulator.py
./src/opendr/perception/multimodal_human_centric/audiovisual_emotion_learner/algorithm/efficientface_utils.py
./src/opendr/perception/multimodal_human_centric/audiovisual_emotion_learner/algorithm/models.py
./src/opendr/perception/multimodal_human_centric/audiovisual_emotion_learner/algorithm/spatial_transforms.py
./src/opendr/perception/multimodal_human_centric/audiovisual_emotion_learner/algorithm/trainer.py
./src/opendr_toolkit_multimodal_human_centric.egg-info/PKG-INFO
./src/opendr_toolkit_multimodal_human_centric.egg-info/SOURCES.txt
./src/opendr_toolkit_multimodal_human_centric.egg-info/dependency_links.txt
./src/opendr_toolkit_multimodal_human_centric.egg-info/requires.txt
./src/opendr_toolkit_multimodal_human_centric.egg-info/top_level.txt
