Metadata-Version: 1.0
Name: opendr-toolkit-multimodal-human-centric
Version: 3.0.0
Summary: Open Deep Learning Toolkit for Robotics (submodule: perception/multimodal_human_centric)
Home-page: https://github.com/opendr-eu/opendr
Author: OpenDR consortium
Author-email: tefas@csd.auth.gr
License: LICENSE
Platform: UNKNOWN
